setup.py
UPCTools.egg-info/PKG-INFO
UPCTools.egg-info/SOURCES.txt
UPCTools.egg-info/dependency_links.txt
UPCTools.egg-info/entry_points.txt
UPCTools.egg-info/not-zip-safe
UPCTools.egg-info/requires.txt
UPCTools.egg-info/top_level.txt
upc_tools/__init__.py
upc_tools/looker.py
upc_tools/release.py
upc_tools/widgets.py
upc_tools/static/spinner.gif
upc_tools/static/upc_tools.js
upc_tools/templates/__init__.py
upc_tools/templates/partial_upc.kid
