Metadata-Version: 1.0
Name: UPCTools
Version: 0.1a1
Summary: A online checking UPC field and a lookup tool
Home-page: UNKNOWN
Author: Claudio Martinez
Author-email: claudio.s.martinez@gmail.com
License: MIT
Keywords: turbogears.widgets
Platform: UNKNOWN
Classifier: Development Status :: 3 - Alpha
Classifier: Operating System :: OS Independent
Classifier: Programming Language :: Python
Classifier: Topic :: Software Development :: Libraries :: Python Modules
Classifier: Framework :: TurboGears
Classifier: Framework :: TurboGears :: Widgets
